cengal_cpu_info/__init__.py
cengal_cpu_info-2.0.1.dist-info/METADATA
cengal_cpu_info-2.0.1.dist-info/WHEEL
cengal_cpu_info-2.0.1.dist-info/licenses/LICENSE.md
cengal_cpu_info-2.0.1.dist-info/licenses/NOTICE
cengal_cpu_info-2.0.1.dist-info/RECORD
